{
    "competence1":{
		"properties":{
			"id":{
				"store": false,
				"type":"long"
			},
			"published":{
				"store": false,
				"type": "boolean"
			},
			"title":{
				"store": false,
				"type":"string"
			},
			"description":{
				"store": false,
				"type":"string"
			},
			"tags":{
				"properties":{
					"title":{
						"store": false,
						"type":"string"
					} 
				}
			},
			"type":{
				"store": false,
				"type":"string"
			},
			"creatorId":{
				"store": false,
				"type":"long"
			}
		}
			
		}

}